paper_trail/__init__.py
paper_trail/async_support.py
paper_trail/config.py
paper_trail/context.py
paper_trail/decorators.py
paper_trail/models.py
paper_trail/performance.py
paper_trail/query.py
paper_trail/reify.py
paper_trail/serializers.py
paper_trail_py-0.1.0.dist-info/METADATA
paper_trail_py-0.1.0.dist-info/WHEEL
paper_trail_py-0.1.0.dist-info/licenses/LICENSE
paper_trail_py-0.1.0.dist-info/RECORD
