Metadata-Version: 2.4
Name: paper-trail-py
Version: 0.1.0
Summary: Modern Python library for tracking changes to SQLAlchemy models
Project-URL: Homepage, https://github.com/yourusername/paper-trail-py
Project-URL: Documentation, https://paper-trail-py.readthedocs.io
Project-URL: Repository, https://github.com/yourusername/paper-trail-py
Project-URL: Issues, https://github.com/yourusername/paper-trail-py/issues
Author-email: alshin <alshin@126.com>
License: MIT
License-File: LICENSE
Keywords: audit,history,sqlalchemy,tracking,versioning
Classifier: Development Status :: 3 - Alpha
Classifier: Intended Audience :: Developers
Classifier: License :: OSI Approved :: MIT License
Classifier: Programming Language :: Python :: 3
Classifier: Programming Language :: Python :: 3.10
Classifier: Programming Language :: Python :: 3.11
Classifier: Programming Language :: Python :: 3.12
Classifier: Topic :: Database
Classifier: Topic :: Software Development :: Libraries :: Python Modules
Requires-Python: >=3.10
Requires-Dist: sqlalchemy>=2.0.0
Provides-Extra: async
Requires-Dist: sqlalchemy[asyncio]>=2.0.0; extra == 'async'
Provides-Extra: dev
Requires-Dist: black>=23.9.0; extra == 'dev'
Requires-Dist: isort>=5.12.0; extra == 'dev'
Requires-Dist: mypy>=1.5.0; extra == 'dev'
Requires-Dist: pre-commit>=3.4.0; extra == 'dev'
Requires-Dist: pytest-asyncio>=0.21.0; extra == 'dev'
Requires-Dist: pytest-cov>=4.1.0; extra == 'dev'
Requires-Dist: pytest>=7.4.0; extra == 'dev'
Requires-Dist: ruff>=0.1.0; extra == 'dev'
Provides-Extra: mysql
Requires-Dist: pymysql>=1.1.0; extra == 'mysql'
Provides-Extra: postgresql
Requires-Dist: psycopg2-binary>=2.9.0; extra == 'postgresql'
